LICENSE.txt
README.md
pyproject.toml
setup.py
reinclined/__init__.py
reinclined.egg-info/PKG-INFO
reinclined.egg-info/SOURCES.txt
reinclined.egg-info/dependency_links.txt
reinclined.egg-info/requires.txt
reinclined.egg-info/top_level.txt
reinclined/helpers/__init__.py
reinclined/helpers/decorator_helpers.py
reinclined/helpers/dictionary_helpers.py
reinclined/helpers/directory_helpers.py
reinclined/helpers/json_helpers.py
reinclined/helpers/list_helpers.py
reinclined/helpers/string_helpers.py
reinclined/logging/__init__.py
reinclined/logging/logger.py
reinclined/models/__init__.py
reinclined/models/code_generator.py
reinclined/models/model_conversion.py
reinclined/proxy/__init__.py
reinclined/proxy/proxy.py
reinclined/pytest/__init__.py
reinclined/pytest/selenium_pytest.py
reinclined/selenium/__init__.py
reinclined/selenium/selenium_appium_shared.py
reinclined/selenium/appium/__init__.py
reinclined/selenium/appium/appium_android.py
reinclined/selenium/appium/appium_factory.py
reinclined/selenium/appium/appium_ios.py
reinclined/selenium/appium/appium_shared.py
reinclined/selenium/selenium/__init__.py
reinclined/selenium/selenium/selenium_extended.py
reinclined/selenium/selenium/selenium_remote.py
reinclined/validations/__init__.py
reinclined/validations/validations.py