Metadata-Version: 2.1
Name: reinclined
Version: 1.3.2
Summary: Tools for UI automation using model based testing ... cloned form https://github.com/rakutentech/ui-automation-tools-mbt with few window adaptation.
Home-page: https://github.com/kirukudenis/reinclined.git
Author: Denis Kiruku
Author-email: denniskiruku@gmail.com
License: UNKNOWN
Platform: UNKNOWN
Classifier: Programming Language :: Python :: 3
Classifier: License :: OSI Approved :: MIT License
Classifier: Operating System :: OS Independent
Requires-Python: >=3.8
License-File: LICENSE.txt
